.gitignore
LICENSE.txt
README.rst
addcopy.sh
gpl_declaration.py
setup.cfg
setup.py
upload.bat
upload.sh
version-bump.sh
test/__init__.py
test/testgen.py
test/testpython.py
test/testracket.py
txt2boil/__init__.py
txt2boil/__main__.py
txt2boil/cmi.py
txt2boil/comments.py
txt2boil/generic_gen.py
txt2boil/langs.py
txt2boil/linegen.py
txt2boil/main.py
txt2boil/pygen.py
txt2boil/version.py
txt2boil.egg-info/PKG-INFO
txt2boil.egg-info/SOURCES.txt
txt2boil.egg-info/dependency_links.txt
txt2boil.egg-info/entry_points.txt
txt2boil.egg-info/top_level.txt
txt2boil/core/__init__.py
txt2boil/core/extractor.py
txt2boil/core/gen.py
txt2boil/core/hookedre.py