Metadata-Version: 1.1
Name: txt2boil
Version: 0.7.2
Summary: Generate boilerplate from source code comments.
Home-page: https://github.com/kcolford/txt2boil
Author: Kieran Colford
Author-email: colfordk@gmail.com
License: GPLv3+
Keywords: boilerplate,comments
Platform: Any
Classifier: Development Status :: 3 - Alpha
Classifier: Environment :: Console
Classifier: Intended Audience :: Developers
Classifier: License :: OSI Approved :: GNU General Public License v3 or later (GPLv3+)
Classifier: Operating System :: OS Independent
Classifier: Natural Language :: English
Classifier: Programming Language :: Python
Classifier: Programming Language :: Python :: 2
Classifier: Programming Language :: Python :: 3
Classifier: Topic :: Software Development :: Code Generators
